analiseBseoo/__init__.py
analiseBseoo/classAnalise.py
analiseBseoo/main.py
analiseBseoo-0.0.11.dist-info/LICENSE
analiseBseoo-0.0.11.dist-info/METADATA
analiseBseoo-0.0.11.dist-info/WHEEL
analiseBseoo-0.0.11.dist-info/top_level.txt
analiseBseoo-0.0.11.dist-info/RECORD
