Metadata-Version: 2.1
Name: analiseBseoo
Version: 0.0.11
Summary: Pacote para analisar o SEO de uma URL
Home-page: https://github.com/elievelton/POO2
Author: Bruna & Elievelton
Author-email: gamessbrunaa@gmail.com, elievelton@gmail.com
License: UNKNOWN
Keywords: python,first package
Platform: UNKNOWN
Classifier: Programming Language :: Python :: 3
Classifier: License :: OSI Approved :: MIT License
Classifier: Operating System :: OS Independent
Requires-Python: >=3.5
License-File: LICENSE
Requires-Dist: urllib3
Requires-Dist: bs4
Requires-Dist: selenium
